{"title":"인기가요","url":"https://program.naver.com/p/658960/clip","favicon":"https://program.naver.com/favicon.ico","elements":[{"title":"도영 - 반딧불 (Little Light) | SBS 240428 방송","contents":"03:52","link":"https://tv.naver.com/v/50549254","retrieved":1714292435259},{"title":"도영 - 새봄의 노래(Beginning) | SBS 240428 방송","contents":"02:23","link":"https://tv.naver.com/v/50549003","retrieved":1714292435259},{"title":"우기((여자)아이들) - FREAK | SBS 240428 방송","contents":"02:56","link":"https://tv.naver.com/v/50549001","retrieved":1714292435263},{"title":"ZEROBASEONE - SWEAT | SBS 240428 방송","contents":"03:30","link":"https://tv.naver.com/v/50548961","retrieved":1714292435263},{"title":"RIIZE - Impossible | SBS 240428 방송","contents":"03:13","link":"https://tv.naver.com/v/50548957","retrieved":1714292435265},{"title":"BOYNEXTDOOR - Earth, Wind & Fire | SBS 240428 방송","contents":"03:06","link":"https://tv.naver.com/v/50548788","retrieved":1714292435266},{"title":"BABYMONSTER - SHEESH | SBS 240428 방송","contents":"03:00","link":"https://tv.naver.com/v/50548439","retrieved":1714292435268},{"title":"이진혁 - Relax | SBS 240428 방송","contents":"02:54","link":"https://tv.naver.com/v/50548398","retrieved":1714292435269},{"title":"원위(ONEWE) - 추억의 소각장(Beautiful Ashes) | SBS 240428 방송","contents":"03:32","link":"https://tv.naver.com/v/50548232","retrieved":1714292435270},{"title":"WOOAH - BLUSH | SBS 240428 방송","contents":"03:05","link":"https://tv.naver.com/v/50548090","retrieved":1714292435272}]}