{"title":"엠카운트다운","url":"https://program.naver.com/p/659252/clip","favicon":"https://program.naver.com/favicon.ico","elements":[{"title":"NEWBEAT(뉴비트) - Flip the Coin | Mnet 250403 방송","contents":"02:54","link":"https://tv.naver.com/v/73383303","retrieved":1743675855003},{"title":"'데뷔 인터뷰' CLOSE YOUR EYES | Mnet 250403 방송","contents":"03:12","link":"https://tv.naver.com/v/73380996","retrieved":1743675855006},{"title":"ONE OR EIGHT - DSTM | Mnet 250403 방송","contents":"02:54","link":"https://tv.naver.com/v/73380995","retrieved":1743675855007},{"title":"이젤(EJel) - 봄은 내 안티 | Mnet 250403 방송","contents":"02:53","link":"https://tv.naver.com/v/73380232","retrieved":1743675855008},{"title":"Xdinary Heroes가 알려주는 이번 주 엠카운트다운 라인업은?","contents":"01:08","link":"https://tv.naver.com/v/73230341","retrieved":1743511493574},{"title":"'최초 공개' 텐 (TEN) - STUNNER | Mnet 250327 방송","contents":"04:08","link":"https://tv.naver.com/v/72867570","retrieved":1743079419511},{"title":"'최초 공개' 텐 (TEN) - BAMBOLA | Mnet 250327 방송","contents":"02:55","link":"https://tv.naver.com/v/72867207","retrieved":1743079419514},{"title":"'단독 공개' 정은지, 서인국 - 커플 (Couple) | Mnet 250327 방송","contents":"04:11","link":"https://tv.naver.com/v/72867194","retrieved":1743079419515},{"title":"더보이즈(THE BOYZ) - VVV | Mnet 250327 방송","contents":"04:00","link":"https://tv.naver.com/v/72866556","retrieved":1743079419515},{"title":"'인터뷰' 정은지(Jeong Eun Ji), 서인국(Seo In Guk) | Mnet 250327 방송","contents":"04:08","link":"https://tv.naver.com/v/72866145","retrieved":1743079419516}]}