{"title":"엠카운트다운","url":"https://program.naver.com/p/659252/clip","favicon":"https://program.naver.com/favicon.ico","elements":[{"title":"'최초 공개' 호시X우지 (SEVENTEEN) - 동갑내기 | Mnet 250313 방송","contents":"04:16","link":"https://tv.naver.com/v/71856774","retrieved":1741869734441},{"title":"'최초 공개' 호시X우지 (SEVENTEEN) - STUPID IDIOT | Mnet 250313 방송","contents":"02:55","link":"https://tv.naver.com/v/71856203","retrieved":1741869734441},{"title":"'최초 공개' 슬기 (SEULGI) - Baby, Not Baby | Mnet 250313 방송","contents":"03:40","link":"https://tv.naver.com/v/71855843","retrieved":1741869734441},{"title":"'인터뷰' 호시X우지 (SEVENTEEN) | Mnet 250313 방송","contents":"03:59","link":"https://tv.naver.com/v/71855829","retrieved":1741869734444},{"title":"'최초 공개' SF9 - LOVE RACE | Mnet 250313 방송","contents":"03:19","link":"https://tv.naver.com/v/71855207","retrieved":1741864699728},{"title":"'최초 공개' 예지 (ITZY) - Air | Mnet 250313 방송","contents":"04:07","link":"https://tv.naver.com/v/71854793","retrieved":1741864699730},{"title":"'소년소녀 엠카백서' 재현&지유와 함께하는 상큼발랄 차트쇼! | Mnet 250313 방송","contents":"06:20","link":"https://tv.naver.com/v/71854788","retrieved":1741864699730},{"title":"'SPECIAL STAGE' 장하오 (ZEROBASEONE) X LUCY - 벚꽃 엔딩 (원곡：버스커 버스커) | Mnet 250313 방송","contents":"04:37","link":"https://tv.naver.com/v/71854088","retrieved":1741864699730},{"title":"'인터뷰' 예지 (ITZY), 슬기 (SEULGI) | Mnet 250313 방송","contents":"05:05","link":"https://tv.naver.com/v/71853685","retrieved":1741864699731},{"title":"'최초 공개' TREASURE(트레저) - YELLOW | Mnet 250313 방송","contents":"03:48","link":"https://tv.naver.com/v/71853677","retrieved":1741864699731}]}