{"title":"뮤직뱅크","url":"https://program.naver.com/p/659774/clip","favicon":"https://program.naver.com/favicon.ico","elements":[{"title":"Red Sun - xikers(싸이커스) | KBS 240412 방송","contents":"03:39","link":"https://tv.naver.com/v/49750045","retrieved":1712913434433},{"title":"HYPERTONIC - TAN(티에이엔) | KBS 240412 방송","contents":"03:03","link":"https://tv.naver.com/v/49750043","retrieved":1712913434433},{"title":"Midas Touch - KISS OF LIFE | KBS 240412 방송","contents":"02:47","link":"https://tv.naver.com/v/49749818","retrieved":1712913434435},{"title":"Broken Heart - 앰퍼샌드원 (AMPERS&ONE) | KBS 240412 방송","contents":"02:58","link":"https://tv.naver.com/v/49749816","retrieved":1712913434437},{"title":"OoWee - NOWADAYS | KBS 240412 방송","contents":"03:05","link":"https://tv.naver.com/v/49749527","retrieved":1712913434442},{"title":"SUPERWOMAN - UNIS(유니스) | KBS 240412 방송","contents":"03:11","link":"https://tv.naver.com/v/49749196","retrieved":1712913434444},{"title":"UhUh - RESCENE (리센느) | KBS 240412 방송","contents":"03:27","link":"https://tv.naver.com/v/49749190","retrieved":1712913434446},{"title":"Pretty good - 세븐어스(SEVENUS) | KBS 240412 방송","contents":"03:43","link":"https://tv.naver.com/v/49748920","retrieved":1712913434447},{"title":"Locked On - VVUP(비비업) | KBS 240412 방송","contents":"03:13","link":"https://tv.naver.com/v/49748029","retrieved":1712913434449},{"title":"Good Girl - Candy Shop | KBS 240412 방송","contents":"02:42","link":"https://tv.naver.com/v/49748023","retrieved":1712913434451}]}