{"title":"뮤직뱅크","url":"https://program.naver.com/p/659774/clip","favicon":"https://program.naver.com/favicon.ico","elements":[{"title":"Pretty Revenge - 키코 (Kik5o) | KBS 240524 방송","contents":"03:12","link":"https://tv.naver.com/v/51844141","retrieved":1716542296552},{"title":"Love seeker - JO1 | KBS 240524 방송","contents":"03:13","link":"https://tv.naver.com/v/51844130","retrieved":1716542296554},{"title":"Gasoline - E’LAST (엘라스트) | KBS 240524 방송","contents":"02:56","link":"https://tv.naver.com/v/51843851","retrieved":1716542296555},{"title":"Ride the Vibe - NEXZ | KBS 240524 방송","contents":"03:13","link":"https://tv.naver.com/v/51843849","retrieved":1716542296556},{"title":"소년...소녀를 만나다 (Girls, Love boys, Love girls) - DXMON(다이몬) | KBS 240524 방송","contents":"03:17","link":"https://tv.naver.com/v/51843577","retrieved":1716542296557},{"title":"TICKET - NOWADAYS | KBS 240524 방송","contents":"03:39","link":"https://tv.naver.com/v/51843291","retrieved":1716542296558},{"title":"Heartthrob - 이스트샤인(EASTSHINE) | KBS 240524 방송","contents":"03:18","link":"https://tv.naver.com/v/51843018","retrieved":1716542296560},{"title":"백점만점 - 트로이카(TROIKA) | KBS 240524 방송","contents":"03:07","link":"https://tv.naver.com/v/51843013","retrieved":1716542296561},{"title":"LOVE ME DO - 어센트(ASC2NT) | KBS 240524 방송","contents":"03:11","link":"https://tv.naver.com/v/51843021","retrieved":1716542296562},{"title":"Baby Step - We；Na  | KBS 240524 방송","contents":"03:03","link":"https://tv.naver.com/v/51843020","retrieved":1716542296564}]}