{"title":"뮤직뱅크","url":"https://program.naver.com/p/659774/clip","favicon":"https://program.naver.com/favicon.ico","elements":[{"title":"청춘에게(Youth2Youth) - EPEX(이펙스) | KBS 240426 방송","contents":"03:21","link":"https://tv.naver.com/v/50478877","retrieved":1714123044496},{"title":"미로(Mirror) - 라포엠(LA POEM) | KBS 240426 방송","contents":"02:50","link":"https://tv.naver.com/v/50478869","retrieved":1714123044497},{"title":"신기루정원 - 김초월 | KBS 240426 방송","contents":"03:15","link":"https://tv.naver.com/v/50478544","retrieved":1714123044498},{"title":"Bomb - ViV | KBS 240426 방송","contents":"03:10","link":"https://tv.naver.com/v/50478534","retrieved":1714123044500},{"title":"Love, Love, Love Love Love! - n.SSign(엔싸인) | KBS 240426 방송","contents":"03:11","link":"https://tv.naver.com/v/50478523","retrieved":1714123044502},{"title":"ROCK THANG - TIOT(티아이오티) | KBS 240426 방송","contents":"03:06","link":"https://tv.naver.com/v/50477993","retrieved":1714123044504},{"title":"SING ! - BEWAVE | KBS 240426 방송","contents":"02:52","link":"https://tv.naver.com/v/50477627","retrieved":1714123044506},{"title":"어린왕자 - 피커스 | KBS 240426 방송","contents":"03:12","link":"https://tv.naver.com/v/50477065","retrieved":1714123044508},{"title":"Deja Vu - 투모로우바이투게더 | KBS 240412 방송","contents":"03:10","link":"https://tv.naver.com/v/49752535","retrieved":1712917049371},{"title":"Bye My Monster - 온앤오프 (ONF) | KBS 240412 방송","contents":"03:51","link":"https://tv.naver.com/v/49751945","retrieved":1712917049373}]}