{"title":"쇼! 음악중심","url":"https://program.naver.com/p/658837/clip","favicon":"https://program.naver.com/favicon.ico","elements":[{"title":"[예능연구소] NMIXX LILY – DASH (엔믹스 릴리 - 대시) FanCam | Show! MusicCore | MBC240120방송","contents":"03:18","link":"https://tv.naver.com/v/46007735","retrieved":1705738791737},{"title":"[예능연구소] NMIXX BAE – DASH (엔믹스 배이 - 대시) FanCam | Show! MusicCore | MBC240120방송","contents":"03:11","link":"https://tv.naver.com/v/46007734","retrieved":1705738791738},{"title":"[예능연구소] NMIXX HAEWON – DASH (엔믹스 해원 - 대시) FanCam | Show! MusicCore | MBC240120방송","contents":"03:20","link":"https://tv.naver.com/v/46007699","retrieved":1705738791738},{"title":"[예능연구소] NMIXX – DASH (엔믹스 – 대시) FanCam | Show! MusicCore | MBC240120방송","contents":"03:15","link":"https://tv.naver.com/v/46007580","retrieved":1705738791739},{"title":"[예능연구소] NMIXX SULLYOON – DASH (엔믹스 설윤 - 대시) FanCam | Show! MusicCore | MBC240120방송","contents":"03:13","link":"https://tv.naver.com/v/46007579","retrieved":1705738791741},{"title":"[예능연구소] NMIXX JIWOO – DASH (엔믹스 지우 - 대시) FanCam | Show! MusicCore | MBC240120방송","contents":"03:15","link":"https://tv.naver.com/v/46007575","retrieved":1705738791746},{"title":"[예능연구소] NMIXX KYUJIN – DASH (엔믹스 규진 - 대시) FanCam | Show! MusicCore | MBC240120방송","contents":"03:58","link":"https://tv.naver.com/v/46007573","retrieved":1705738791748},{"title":"씨스타19 - 노 모어 (SISTAR19 - NO MORE (MA BOY)), MBC 240120 방송","contents":"02:53","link":"https://tv.naver.com/v/46007459","retrieved":1705738791749},{"title":"씨스타19 - 소우시 (SISTAR19 - SAUCY), MBC 240120 방송","contents":"01:28","link":"https://tv.naver.com/v/46007360","retrieved":1705738791750},{"title":"비원에이포 - 리와인드 (B1A4 - REWIND), MBC 240120 방송","contents":"03:17","link":"https://tv.naver.com/v/46007342","retrieved":1705738791751}]}