{"title":"더쇼","url":"https://program.naver.com/p/3235720/clip","favicon":"https://program.naver.com/favicon.ico","elements":[{"title":"EPEX(이펙스) - Breathe in Love [THE SHOW 240416]","contents":"03:24","link":"https://tv.naver.com/v/49933274","retrieved":1713262643336},{"title":"KISS OF LIFE - Midas Touch [THE SHOW 240416]","contents":"02:55","link":"https://tv.naver.com/v/49933273","retrieved":1713262643337},{"title":"[챌린딩] MC 형준 & 아일릿(ILLIT) [THE SHOW 240416]","contents":"03:12","link":"https://tv.naver.com/v/49933270","retrieved":1713262643338},{"title":"UNIS(유니스) - SUPERWOMAN [THE SHOW 240416]","contents":"03:21","link":"https://tv.naver.com/v/49932979","retrieved":1713262643343},{"title":"UNIS(유니스) - Dopamine(UNIS Ver.) [THE SHOW 240416]","contents":"03:28","link":"https://tv.naver.com/v/49932721","retrieved":1713262643345},{"title":"앰퍼샌드원(AMPERS&ONE) - Someday [THE SHOW 240416]","contents":"03:11","link":"https://tv.naver.com/v/49932717","retrieved":1713262643347},{"title":"KISS OF LIFE - Nothing [THE SHOW 240416]","contents":"03:37","link":"https://tv.naver.com/v/49932172","retrieved":1713262643349},{"title":"NOWADAYS - OoWee [THE SHOW 240416]","contents":"03:12","link":"https://tv.naver.com/v/49931818","retrieved":1713262643350},{"title":"엔카이브(NCHIVE) - Racer [THE SHOW 240416]","contents":"03:08","link":"https://tv.naver.com/v/49931480","retrieved":1713262643354},{"title":"Candy Shop  - Good Girl [THE SHOW 240416]","contents":"02:48","link":"https://tv.naver.com/v/49931205","retrieved":1713262643354}]}